{
  "profiles": [
    {
      "profileName": "NR_NAQAACAAJ Profile",
      "bookItem": {
        "id": "NR_NAQAACAAJ",
        "title": "Dünün Dünyasi",
        "imageLink": "http://books.google.com/books/content?id=NR_NAQAACAAJ&printsec=frontcover&img=1&zoom=5&source=gbs_api",
        "authors": "Stefan Zweig",
        "infoLink": "http://books.google.com.tr/books?id=NR_NAQAACAAJ&dq=stefan+zweig&hl=&source=gbs_api"
      },
      "id": 6
    },
    {
      "profileName": "FZrsDwAAQBAJ Profile",
      "bookItem": {
        "id": "FZrsDwAAQBAJ",
        "title": "Satranç - Stefan Zweig",
        "description": "Bir kez daha hayretler içinde kaldık. Onun hesaplamalarındaki doğruluk ve hızda bizi afallatan bir şey vardı; sanki hamleleri bir kitap okuyup söylüyor gibiydi. Her halükarda onun oyuna müdahele etmesi ve bir dünya şampiyonuyla berabere kalmanın beklenmedik fırsatı büyülü bir etki yaratmıştı. Tahtayı daha iyi görmesi için kenara çekildik. McConnor. Şahı g8den h7ye ilerletiyorum, değil mi? diye sordu yeniden.20. yüzyılı en iyi anlayıp yorumlayan yazarlardan bir tanesidir Stefan Zweig. 1. Dünya Savaşının yıkımı, ardından Nazizmin yükselişiyle başlayan 2. Dünya Savaşının getirdiği alt üst oluşu bütün açıklığıyla okurun önüne serer.Kısa aralıklarla yaşanan iki büyük savaşın insan bilicinde meydana getirdiği tahribatı sıradan insanları modelleyerek anlatir. Karamsarlık, kötümserlik, ümitsizlik Zweigın metinlerini siyah birtül gibi örter.Stefan Zweig akıcı anlatımı, keskin üslubu. karakter oluşturmasındaki ustalığın yanında çağına yaptığı doğru tanıklıkla klasik yazarlar arasına ismini yazdırmıştır.",
        "imageLink": "http://books.google.com/books/content?id=FZrsDwAAQBAJ&printsec=frontcover&img=1&zoom=5&edge=curl&source=gbs_api",
        "authors": "Stefan Zweig",
        "infoLink": "https://play.google.com/store/books/details?id=FZrsDwAAQBAJ&source=gbs_api",
        "publisher": "Aperatif Kitap Yayınları"
      },
      "id": 7
    }
  ]
}